electionguard/__init__.py
electionguard/ballot.py
electionguard/ballot_box.py
electionguard/ballot_code.py
electionguard/ballot_compact.py
electionguard/ballot_validator.py
electionguard/big_integer.py
electionguard/byte_padding.py
electionguard/chaum_pedersen.py
electionguard/constants.py
electionguard/data_store.py
electionguard/decrypt_with_secrets.py
electionguard/decrypt_with_shares.py
electionguard/decryption.py
electionguard/decryption_mediator.py
electionguard/decryption_share.py
electionguard/discrete_log.py
electionguard/election.py
electionguard/election_object_base.py
electionguard/election_polynomial.py
electionguard/elgamal.py
electionguard/encrypt.py
electionguard/group.py
electionguard/guardian.py
electionguard/hash.py
electionguard/hmac.py
electionguard/key_ceremony.py
electionguard/key_ceremony_mediator.py
electionguard/logs.py
electionguard/manifest.py
electionguard/nonces.py
electionguard/proof.py
electionguard/py.typed
electionguard/scheduler.py
electionguard/schnorr.py
electionguard/serialize.py
electionguard/singleton.py
electionguard/tally.py
electionguard/type.py
electionguard/utils.py
electionguard_cli/__init__.py
electionguard_cli/cli_models/__init__.py
electionguard_cli/cli_models/cli_decrypt_results.py
electionguard_cli/cli_models/cli_election_inputs_base.py
electionguard_cli/cli_models/e2e_build_election_results.py
electionguard_cli/cli_models/encrypt_results.py
electionguard_cli/cli_models/mark_results.py
electionguard_cli/cli_models/submit_results.py
electionguard_cli/cli_steps/__init__.py
electionguard_cli/cli_steps/cli_step_base.py
electionguard_cli/cli_steps/decrypt_step.py
electionguard_cli/cli_steps/election_builder_step.py
electionguard_cli/cli_steps/encrypt_votes_step.py
electionguard_cli/cli_steps/input_retrieval_step_base.py
electionguard_cli/cli_steps/key_ceremony_step.py
electionguard_cli/cli_steps/mark_ballots_step.py
electionguard_cli/cli_steps/output_step_base.py
electionguard_cli/cli_steps/print_results_step.py
electionguard-1.4.0.dist-info/entry_points.txt
electionguard-1.4.0.dist-info/LICENSE
electionguard-1.4.0.dist-info/WHEEL
electionguard-1.4.0.dist-info/METADATA
electionguard-1.4.0.dist-info/RECORD
