Metadata-Version: 2.1
Name: electionguard
Version: 1.4.0
Summary: ElectionGuard: Support for e2e verified elections.
Home-page: https://microsoft.github.io/electionguard-python
License: MIT
Author: Microsoft
Author-email: electionguard@microsoft.com
Requires-Python: >=3.9.5,<4.0.0
Classifier: Development Status :: 5 - Production/Stable
Classifier: Intended Audience :: Developers
Classifier: License :: OSI Approved :: MIT License
Classifier: Operating System :: MacOS
Classifier: Operating System :: Microsoft :: Windows
Classifier: Operating System :: POSIX
Classifier: Operating System :: Unix
Classifier: Programming Language :: Python
Classifier: Programming Language :: Python :: 3
Classifier: Programming Language :: Python :: 3.10
Classifier: Topic :: Utilities
Requires-Dist: Eel[jinja2] (>=0.14.0,<0.15.0)
Requires-Dist: click (>=8.1.0,<9.0.0)
Requires-Dist: dacite (>=1.6.0,<2.0.0)
Requires-Dist: dependency-injector (>=4.39.1,<5.0.0)
Requires-Dist: gmpy2 (>=2.0.8,<3.0.0)
Requires-Dist: psutil (>=5.7.2)
Requires-Dist: pydantic (==1.9.0)
Requires-Dist: pymongo (>=4.1.1,<5.0.0)
Requires-Dist: pytest-mock (>=3.8.2,<4.0.0)
Requires-Dist: python-dateutil (>=2.8.2,<3.0.0)
Requires-Dist: types-python-dateutil (>=2.8.14,<3.0.0)
Project-URL: Documentation, https://microsoft.github.io/electionguard-python
Project-URL: GitHub Pages, https://microsoft.github.io/electionguard-python
Project-URL: Issue Tracker, https://github.com/microsoft/electionguard-python/issues
Project-URL: Milestones, https://github.com/microsoft/electionguard-python/milestones
Project-URL: Repository, https://github.com/microsoft/electionguard-python
Project-URL: Read the Docs, https://electionguard-python.readthedocs.io
Project-URL: Releases, https://github.com/microsoft/electionguard-python/releases
